opes/__init__.py
opes/backtester.py
opes/errors.py
opes/utils.py
opes/methods/__init__.py
opes/methods/base_optimizer.py
opes/methods/distributionally_robust.py
opes/methods/heuristics.py
opes/methods/markowitz.py
opes/methods/online.py
opes/methods/risk_metrics.py
opes/methods/utility_theory.py
opes-0.5.2.dist-info/licenses/LICENSE
opes-0.5.2.dist-info/METADATA
opes-0.5.2.dist-info/WHEEL
opes-0.5.2.dist-info/top_level.txt
opes-0.5.2.dist-info/RECORD
