Metadata-Version: 2.4
Name: opes
Version: 0.5.2
Summary: A Research-focused portfolio optimization and backtesting engine.
Author-email: Nitin Tony Paul <nitintonypaul@gmail.com>
License: MIT
Project-URL: repository, https://github.com/opes-core/opes
Project-URL: documentation, https://github.com/opes-core/opes-documentation
Project-URL: book, https://opes.pages.dev
Classifier: Development Status :: 4 - Beta
Classifier: Programming Language :: Python :: 3
Classifier: Programming Language :: Python :: 3.10
Classifier: License :: OSI Approved :: MIT License
Classifier: Operating System :: OS Independent
Classifier: Topic :: Office/Business :: Financial :: Investment
Requires-Python: >=3.10
License-File: LICENSE
Requires-Dist: numpy<3.0,>=2.2.6
Requires-Dist: pandas<3.0,>=2.3.3
Requires-Dist: scipy<2.0,>=1.15.2
Requires-Dist: matplotlib<4.0,>=3.10.1
Dynamic: license-file
